{"organizations": [], "uuid": "f0c0ed331a3d02fbf170dfb5d93e3fbd3e16e8d8", "thread": {"social": {"gplus": {"shares": 0}, "pinterest": {"shares": 0}, "vk": {"shares": 0}, "linkedin": {"shares": 0}, "facebook": {"likes": 0, "shares": 0, "comments": 0}, "stumbledupon": {"shares": 0}}, "site_full": "www.wsj.com", "main_image": "https://si.wsj.net/img/WSJ_Logo_black_social.gif", "site_section": "https://www.wsj.com/europe", "section_title": "The Wall Street Journal &amp; Breaking News, Business, Financial and Economic News, World News and Video", "url": "https://www.wsj.com/articles/ambitious-apple-store-put-up-for-sale-by-chicago-landlord-1521656697", "country": "US", "domain_rank": 387, "title": "‘Ambitious’ Apple Store Put Up For Sale by Chicago Landlord", "performance_score": 0, "site": "wsj.com", "participants_count": 1, "title_full": "", "spam_score": 0.015, "site_type": "news", "published": "2018-03-21T21:24:00.000+02:00", "replies_count": 0, "uuid": "f0c0ed331a3d02fbf170dfb5d93e3fbd3e16e8d8"}, "author": "WSJ Real Estate", "url": "https://www.wsj.com/articles/ambitious-apple-store-put-up-for-sale-by-chicago-landlord-1521656697", "ord_in_thread": 0, "title": "‘Ambitious’ Apple Store Put Up For Sale by Chicago Landlord", "locations": [], "entities": {"persons": [], "locations": [{"name": "chicago", "sentiment": "none"}, {"name": "new york", "sentiment": "none"}, {"name": "u.s.", "sentiment": "none"}, {"name": "manhattan", "sentiment": "none"}], "organizations": [{"name": "chelsea market", "sentiment": "none"}, {"name": "apple inc.", "sentiment": "none"}, {"name": "chelsea market seeks to replicate success in other cities google", "sentiment": "none"}]}, "highlightText": "", "language": "english", "persons": [], "text": "COMMERCIAL REAL ESTATE ‘Ambitious’ Apple Store Put Up For Sale by Chicago Landlord The Chicago landlord of what Apple Inc. calls its “most ambitious store” has put the building on the block in a sales process that will test the power of the popular brand name in a tempestuous retail climate.\nU.S. Existing Home Sales Rose Robustly in February New York’s Chelsea Market Seeks to Replicate Success in Other Cities\nGoogle closed on its record $2.4 billion purchase of the Chelsea Market building in Manhattan on Tuesday,... ", "external_links": [], "published": "2018-03-21T21:24:00.000+02:00", "crawled": "2018-03-22T00:47:28.047+02:00", "highlightTitle": ""}