{"organizations": [], "uuid": "18c44c1afeb6c428fc4d5624eb66546670e7e3b3", "thread": {"social": {"gplus": {"shares": 0}, "pinterest": {"shares": 0}, "vk": {"shares": 0}, "linkedin": {"shares": 0}, "facebook": {"likes": 0, "shares": 0, "comments": 0}, "stumbledupon": {"shares": 0}}, "site_full": "www.wsj.com", "main_image": "https://si.wsj.net/img/WSJ_Logo_black_social.gif", "site_section": "https://www.wsj.com/news/markets", "section_title": "Stock Market &amp; Finance News - Wall Street Journal", "url": "https://www.wsj.com/articles/u-s-dollar-edges-higher-1521043683", "country": "US", "domain_rank": 387, "title": "U.S. Dollar Edges Higher", "performance_score": 0, "site": "wsj.com", "participants_count": 1, "title_full": "", "spam_score": 0.904, "site_type": "news", "published": "2018-03-14T19:08:00.000+02:00", "replies_count": 0, "uuid": "18c44c1afeb6c428fc4d5624eb66546670e7e3b3"}, "author": "Daniel Kruger", "url": "https://www.wsj.com/articles/u-s-dollar-edges-higher-1521043683", "ord_in_thread": 0, "title": "U.S. Dollar Edges Higher", "locations": [], "entities": {"persons": [], "locations": [{"name": "u.s.", "sentiment": "none"}], "organizations": [{"name": "commerce department", "sentiment": "none"}]}, "highlightText": "", "language": "english", "persons": [], "text": "The U.S. dollar edged higher as some investors adopted the view that inflation will accelerate over a longer timetable.\nThe WSJ Dollar Index, which measures the currency against a basket of 16 others, rose less than 0.1% to 83.59. The dollar gained against the euro and declined versus the yen.\nThe dollar was weighed down by a Commerce Department... ", "external_links": [], "published": "2018-03-14T19:08:00.000+02:00", "crawled": "2018-03-14T23:30:46.036+02:00", "highlightTitle": ""}