{"organizations": [], "uuid": "31ba0fa5824fe054959dff7b1d5fd03c71f3f154", "thread": {"social": {"gplus": {"shares": 0}, "pinterest": {"shares": 0}, "vk": {"shares": 0}, "linkedin": {"shares": 0}, "facebook": {"likes": 0, "shares": 0, "comments": 0}, "stumbledupon": {"shares": 0}}, "site_full": "www.cnbc.com", "main_image": "https://fm.cnbc.com/applications/cnbc.com/resources/img/editorial/2018/03/08/105051775-5ED2-SBE-030818-Nolting.600x400.jpg", "site_section": "", "section_title": "", "url": "https://www.cnbc.com/video/2018/03/08/expect-ecb-to-change-forward-guidance-today-deutsche-bank-wealth-management.html", "country": "US", "domain_rank": 767, "title": "Expect ECB to change forward guidance today: Deutsche Bank Wealth Management", "performance_score": 0, "site": "cnbc.com", "participants_count": 0, "title_full": "", "spam_score": 0.909, "site_type": "news", "published": "2018-03-08T11:21:00.000+02:00", "replies_count": 0, "uuid": "31ba0fa5824fe054959dff7b1d5fd03c71f3f154"}, "author": "", "url": "https://www.cnbc.com/video/2018/03/08/expect-ecb-to-change-forward-guidance-today-deutsche-bank-wealth-management.html", "ord_in_thread": 0, "title": "Expect ECB to change forward guidance today: Deutsche Bank Wealth Management", "locations": [], "entities": {"persons": [], "locations": [], "organizations": [{"name": "ecb", "sentiment": "negative"}, {"name": "deutsche bank wealth management expect ecb", "sentiment": "negative"}, {"name": "deutsche bank wealth management", "sentiment": "negative"}, {"name": "european central bank", "sentiment": "none"}]}, "highlightText": "", "language": "english", "persons": [], "text": "Expect ECB to change forward guidance today: Deutsche Bank Wealth Management 1 Hour Ago Christian Nolting, global chief investment officer at Deutsche Bank Wealth Management, speaks about potential policy moves by the European Central Bank.", "external_links": [], "published": "2018-03-08T11:21:00.000+02:00", "crawled": "2018-03-08T11:25:30.013+02:00", "highlightTitle": ""}