{"organizations": [], "uuid": "054866b1d0e15500eede48e5fbe473e470334886", "thread": {"social": {"gplus": {"shares": 0}, "pinterest": {"shares": 0}, "vk": {"shares": 0}, "linkedin": {"shares": 5}, "facebook": {"likes": 1, "shares": 1, "comments": 0}, "stumbledupon": {"shares": 0}}, "site_full": "www.cnbc.com", "main_image": "https://fm.cnbc.com/applications/cnbc.com/resources/img/editorial/2018/02/02/104984072-5ED2-CAP-RyanRoberts-020118.600x400.jpg", "site_section": "http://www.cnbc.com/id/100004038/device/rss/rss.html", "section_title": "Latest Video", "url": "https://www.cnbc.com/video/2018/02/01/why-did-alibaba-shares-sell-off.html", "country": "US", "domain_rank": 767, "title": "Why did Alibaba shares sell off?", "performance_score": 0, "site": "cnbc.com", "participants_count": 0, "title_full": "", "spam_score": 0.0, "site_type": "news", "published": "2018-02-02T06:38:00.000+02:00", "replies_count": 0, "uuid": "054866b1d0e15500eede48e5fbe473e470334886"}, "author": "", "url": "https://www.cnbc.com/video/2018/02/01/why-did-alibaba-shares-sell-off.html", "ord_in_thread": 0, "title": "Why did Alibaba shares sell off?", "locations": [], "entities": {"persons": [{"name": "ryan roberts", "sentiment": "none"}], "locations": [], "organizations": [{"name": "alibaba", "sentiment": "negative"}, {"name": "mcm partners", "sentiment": "none"}]}, "highlightText": "", "language": "english", "persons": [], "text": "Why did Alibaba shares sell off? 2 Hours Ago Alibaba shares dipped even though the company reported earnings that beat expectations. MCM Partners' Ryan Roberts weighs in.", "external_links": [], "published": "2018-02-02T06:38:00.000+02:00", "crawled": "2018-02-02T08:53:40.001+02:00", "highlightTitle": ""}