{"organizations": [], "uuid": "fbc73006f15275d19bf9eedf4245bd19dbb31b74", "thread": {"social": {"gplus": {"shares": 0}, "pinterest": {"shares": 0}, "vk": {"shares": 0}, "linkedin": {"shares": 0}, "facebook": {"likes": 0, "shares": 0, "comments": 0}, "stumbledupon": {"shares": 0}}, "site_full": "www.cnbc.com", "main_image": "https://fm.cnbc.com/applications/cnbc.com/resources/img/editorial/2015/11/13/103167026-IMG_8692rr.1910x1000.jpg", "site_section": "", "section_title": "", "url": "https://www.cnbc.com/2018/02/20/reit-kimco-to-benefit-from-albertsons-acquisition-of-rite-aid.html", "country": "US", "domain_rank": 767, "title": "REIT Kimco to benefit from Albertsons' acquisition of Rite Aid", "performance_score": 0, "site": "cnbc.com", "participants_count": 0, "title_full": "", "spam_score": 0.249, "site_type": "news", "published": "2018-02-20T21:37:00.000+02:00", "replies_count": 0, "uuid": "fbc73006f15275d19bf9eedf4245bd19dbb31b74"}, "author": "Lauren Thomas", "url": "https://www.cnbc.com/2018/02/20/reit-kimco-to-benefit-from-albertsons-acquisition-of-rite-aid.html", "ord_in_thread": 0, "title": "REIT Kimco to benefit from Albertsons' acquisition of Rite Aid", "locations": [], "entities": {"persons": [{"name": "kim", "sentiment": "negative"}, {"name": "conor flynn", "sentiment": "none"}], "locations": [{"name": "laguna niguel", "sentiment": "none"}, {"name": "california", "sentiment": "none"}, {"name": "u.s.", "sentiment": "none"}, {"name": "boise", "sentiment": "none"}, {"name": "amazon", "sentiment": "none"}], "organizations": [{"name": "rite aid scott mlyn", "sentiment": "negative"}, {"name": "albertsons", "sentiment": "negative"}, {"name": "kimco", "sentiment": "negative"}, {"name": "cnbc an albertsons", "sentiment": "negative"}, {"name": "walmart", "sentiment": "none"}, {"name": "btig research", "sentiment": "none"}]}, "highlightText": "", "language": "english", "persons": [], "text": "Real estate investment trust Kimco Realty is poised to be one beneficiary of Albertsons acquiring Rite Aid.  ", "external_links": [], "published": "2018-02-20T21:37:00.000+02:00", "crawled": "2018-02-20T21:37:59.136+02:00", "highlightTitle": ""}