{"organizations": [], "uuid": "68d794c1565972449294a95c876478a4d175f542", "thread": {"social": {"gplus": {"shares": 0}, "pinterest": {"shares": 0}, "vk": {"shares": 0}, "linkedin": {"shares": 0}, "facebook": {"likes": 0, "shares": 0, "comments": 0}, "stumbledupon": {"shares": 0}}, "site_full": "www.cnbc.com", "main_image": "", "site_section": "http://www.cnbc.com/id/10000027/page/11", "section_title": "Press Releases - CNBC", "url": "http://www.cnbc.com/2018/04/19/pr-newswire-wec-energy-group-declares-quarterly-dividend.html", "country": "US", "domain_rank": 767, "title": "WEC Energy Group declares quarterly dividend", "performance_score": 0, "site": "cnbc.com", "participants_count": 1, "title_full": "", "spam_score": 0.55, "site_type": "news", "published": "2018-04-19T21:31:00.000+03:00", "replies_count": 0, "uuid": "68d794c1565972449294a95c876478a4d175f542"}, "author": "cnbc.com", "url": "http://www.cnbc.com/2018/04/19/pr-newswire-wec-energy-group-declares-quarterly-dividend.html", "ord_in_thread": 0, "title": "WEC Energy Group declares quarterly dividend", "locations": [], "entities": {"persons": [], "locations": [{"name": "milwaukee", "sentiment": "none"}, {"name": "milwaukee", "sentiment": "none"}, {"name": "north shore gas", "sentiment": "none"}, {"name": "illinois", "sentiment": "none"}, {"name": "minnesota", "sentiment": "none"}, {"name": "wisconsin", "sentiment": "none"}, {"name": "michigan", "sentiment": "none"}], "organizations": [{"name": "wec", "sentiment": "negative"}, {"name": "wec energy group", "sentiment": "negative"}, {"name": "nyse", "sentiment": "negative"}, {"name": "upper michigan energy resources", "sentiment": "none"}, {"name": "wisconsin public service", "sentiment": "none"}, {"name": "s&p", "sentiment": "none"}, {"name": "minnesota energy resources", "sentiment": "none"}]}, "highlightText": "", "language": "english", "persons": [], "text": "MILWAUKEE, The board of directors of WEC Energy Group (NYSE: WEC) today declared a quarterly cash dividend of 55.25 cents per share on the company's common stock.\nThe dividend is payable June 1, 2018, to stockholders of record on May 14, 2018. This marks the 303 rd consecutive quarter – dating back to 1942 – that the company will have paid a dividend to its stockholders.\nWEC Energy Group (NYSE: WEC), based in Milwaukee, is one of the nation's premier energy companies, serving 4.5 million customers in Wisconsin, Illinois, Michigan and Minnesota.\nThe company's principal utilities are We Energies, Wisconsin Public Service, Peoples Gas, North Shore Gas, Michigan Gas Utilities, Minnesota Energy Resources and Upper Michigan Energy Resources. The company's other major subsidiary, We Power, designs, builds and owns electric generating plants.\nWEC Energy Group ( wecenergygroup.com ), is a Fortune 500 company and a component of the S&P 500. The company has approximately 50,000 stockholders of record, 8,000 employees, and more than $31 billion of assets.\nView original content: http://www.prnewswire.com/news-releases/wec-energy-group-declares-quarterly-dividend-300633195.html\nSOURCE WEC Energy Group", "external_links": ["http://www.wecenergygroup.com/", "http://www.prnewswire.com/news-releases/wec-energy-group-declares-quarterly-dividend-300633195.html"], "published": "2018-04-19T21:31:00.000+03:00", "crawled": "2018-04-20T00:45:21.015+03:00", "highlightTitle": ""}