{"organizations": [], "uuid": "cfae124cd25ce1703f6298a377a6a1ff118555dc", "thread": {"social": {"gplus": {"shares": 0}, "pinterest": {"shares": 0}, "vk": {"shares": 0}, "linkedin": {"shares": 0}, "facebook": {"likes": 5, "shares": 5, "comments": 0}, "stumbledupon": {"shares": 0}}, "site_full": "www.wsj.com", "main_image": "https://si.wsj.net/public/resources/images/B3-AD820_NYBLEE_SOC_20180422113110.jpg", "site_section": "https://www.wsj.com/europe", "section_title": "The Wall Street Journal &amp; Breaking News, Business, Financial and Economic News, World News and Video", "url": "https://www.wsj.com/articles/brookfield-plans-retail-reboot-on-bleecker-street-1524402875", "country": "US", "domain_rank": 387, "title": "Brookfield Plans Retail Reboot on Bleecker Street", "performance_score": 0, "site": "wsj.com", "participants_count": 1, "title_full": "", "spam_score": 0.958, "site_type": "news", "published": "2018-04-22T17:14:00.000+03:00", "replies_count": 0, "uuid": "cfae124cd25ce1703f6298a377a6a1ff118555dc"}, "author": "Keiko Morris", "url": "https://www.wsj.com/articles/brookfield-plans-retail-reboot-on-bleecker-street-1524402875", "ord_in_thread": 0, "title": "Brookfield Plans Retail Reboot on Bleecker Street", "locations": [], "entities": {"persons": [{"name": "christopher", "sentiment": "negative"}], "locations": [{"name": "manhattan", "sentiment": "none"}, {"name": "brookfield", "sentiment": "none"}], "organizations": [{"name": "bank", "sentiment": "negative"}, {"name": "brookfield property partners lp", "sentiment": "none"}]}, "highlightText": "", "language": "english", "persons": [], "text": "The stretch of Manhattan’s Bleecker Street between Bank and Christopher streets is pockmarked with “for lease” signs, a casualty from the collision of the retail industry’s upheaval and skyrocketing rents.\nBut for Brookfield Property Partners LP, this is the land of opportunity. The global real-estate developer and investor closed a deal to acquire four retail properties with seven storefronts on Bleecker Street.\n“There’s... ", "external_links": [], "published": "2018-04-22T17:14:00.000+03:00", "crawled": "2018-04-23T04:15:37.026+03:00", "highlightTitle": ""}